<LINEARUNITLIST>
     <LINEARUNIT>
           <NAME>Chain_Benoit_1895_A</NAME>
           <UNIT>20.1167824</UNIT>
     </LINEARUNIT>
     <LINEARUNIT>
           <NAME>Chain_Benoit_1895_B</NAME>
           <UNIT>20.1167824943759</UNIT>
     </LINEARUNIT>
     <LINEARUNIT>
           <NAME>Chain_Clarke</NAME>
           <UNIT>20.11661949</UNIT>
     </LINEARUNIT>
     <LINEARUNIT>
           <NAME>Chain_Sears</NAME>
           <UNIT>20.1167651215526</UNIT>
     </LINEARUNIT>
     <LINEARUNIT>
           <NAME>Chain_US</NAME>
           <UNIT>20.1168402336805</UNIT>
     </LINEARUNIT>
     <LINEARUNIT>
           <NAME>Fathom</NAME>
           <UNIT>1.8288</UNIT>
     </LINEARUNIT>
     <LINEARUNIT>
           <NAME>Foot</NAME>
           <UNIT>0.3048</UNIT>
     </LINEARUNIT>
     <LINEARUNIT>
           <NAME>Foot_1865</NAME>
           <UNIT>0.304800833333333</UNIT>
     </LINEARUNIT>
     <LINEARUNIT>
           <NAME>Meter</NAME>
           <UNIT>1</UNIT>
     </LINEARUNIT>
</LINEARUNITLIST>
